nonebot_dcqq_relay_plugin/__init__.py
nonebot_dcqq_relay_plugin/config.py
nonebot_dcqq_relay_plugin/setup.py
nonebot_dcqq_relay_plugin/Adapters/Discord.py
nonebot_dcqq_relay_plugin/Adapters/QQ.py
nonebot_dcqq_relay_plugin/Adapters/__init__.py
nonebot_dcqq_relay_plugin/Core/__init__.py
nonebot_dcqq_relay_plugin/Core/constants.py
nonebot_dcqq_relay_plugin/Core/global_functions.py
nonebot_dcqq_relay_plugin/Database/__init__.py
nonebot_dcqq_relay_plugin/Database/db.py
nonebot_dcqq_relay_plugin/Database/models.py
nonebot_dcqq_relay_plugin/Handlers/Discord.py
nonebot_dcqq_relay_plugin/Handlers/QQ.py
nonebot_dcqq_relay_plugin/Handlers/__init__.py
nonebot_dcqq_relay_plugin-1.1.3.dist-info/LICENSE
nonebot_dcqq_relay_plugin-1.1.3.dist-info/METADATA
nonebot_dcqq_relay_plugin-1.1.3.dist-info/WHEEL
nonebot_dcqq_relay_plugin-1.1.3.dist-info/top_level.txt
nonebot_dcqq_relay_plugin-1.1.3.dist-info/RECORD
