Metadata-Version: 2.1
Name: nonebot_dcqq_relay_plugin
Version: 1.1.3
Summary: 使用Nonebot2让Discord和QQ群实现互相通信
Home-page: https://github.com/PawTeamClub/nonebot_dcqq_relay_plugin
Author: Robonyantame
Author-email: robonyantame@gmail.com
Classifier: License :: OSI Approved :: MIT License
Classifier: Programming Language :: Python :: 3
Requires-Python: >=3.8, <4.0
License-File: LICENSE
Requires-Dist: nonebot2 >=2.3.1
Requires-Dist: nonebot-adapter-onebot >=2.4.3
Requires-Dist: nonebot-adapter-discord >=0.1.8
Requires-Dist: nonebot2[fastapi] >=2.3.1
Requires-Dist: nonebot2[httpx] >=2.3.1
Requires-Dist: nonebot2[websockets] >=2.3.1
Requires-Dist: tortoise-orm >=0.21.4
Requires-Dist: aiohttp >=3.9.5
Requires-Dist: moviepy >=1.0.3
Requires-Dist: imageio >=2.34.2
Requires-Dist: pyrlottie >=2024.0.1
Requires-Dist: Pillow >=10.4.0
